.DS_Store
.gitignore
LICENSE.txt
MANIFEST.in
README.md
setup.cfg
setup.py
AbrIO.egg-info/PKG-INFO
AbrIO.egg-info/SOURCES.txt
AbrIO.egg-info/dependency_links.txt
AbrIO.egg-info/entry_points.txt
AbrIO.egg-info/not-zip-safe
AbrIO.egg-info/requires.txt
AbrIO.egg-info/top_level.txt
abriocli/__init__.py
abriocli/abrio.py
abriocli/component/__init__.py
abriocli/component/component.py
abriocli/conf/__init__.py
abriocli/conf/conf.py
abriocli/project/__init__.py
abriocli/project/project.py
abriocli/util/__init__.py
abriocli/util/checker.py
abriocli/util/file.py