Metadata-Version: 1.1
Name: AbrIO
Version: 0.0.5
Summary: Abrio Engine cli for developers
Home-page: https://github.com/kianenigma/abrio-cli
Author: AbrIO
Author-email: abrioengine@gmail.com
License: UNKNOWN
Download-URL: https://github.com/kianenigma/abrio-cli/archive/0.0.43.tar.gz
Platform: UNKNOWN
